troublebox/__init__.py
troublebox/app.py
troublebox/models.py
troublebox/alembic/env.py
troublebox/alembic/versions/604d83a8c90e_add_projects_table.py
troublebox/alembic/versions/ccb528164bd7_initial_db.py
troublebox/templates/event.pt
troublebox/templates/index.pt
troublebox-0.3.2.dist-info/LICENSE
troublebox-0.3.2.dist-info/METADATA
troublebox-0.3.2.dist-info/WHEEL
troublebox-0.3.2.dist-info/entry_points.txt
troublebox-0.3.2.dist-info/top_level.txt
troublebox-0.3.2.dist-info/RECORD
