Metadata-Version: 2.1
Name: troublebox
Version: 0.3.2
Summary: A very limited Sentry compatible end point
Home-page: https://github.com/fschulze/troublebox
Author: Florian Schulze and Contributors
Author-email: mail@florian-schulze.net
License: BSD
Platform: UNKNOWN
Requires-Dist: SQLAlchemy
Requires-Dist: alembic
Requires-Dist: lazy
Requires-Dist: pyramid (>=2)
Requires-Dist: pyramid-chameleon
Requires-Dist: pyramid-retry
Requires-Dist: pyramid-tm
Requires-Dist: transaction
Requires-Dist: waitress
Requires-Dist: zope.sqlalchemy
